parivaha/.config/env.example
parivaha/.config/sample_payload.json
parivaha/.config/sync_config.json
parivaha/.config/sync_log.json
parivaha/__init__.py
parivaha/cli.py
parivaha/config.py
parivaha/obsidian_io.py
parivaha/progress.py
parivaha/seed.py
parivaha/sync.py
parivaha/utils.py
parivaha/vault.py
parivaha-0.1.16.dist-info/LICENSE
parivaha-0.1.16.dist-info/METADATA
parivaha-0.1.16.dist-info/WHEEL
parivaha-0.1.16.dist-info/entry_points.txt
parivaha-0.1.16.dist-info/RECORD
