Metadata-Version: 2.1
Name: parivaha
Version: 0.1.16
Summary: 
Author: Suhail
Author-email: suhailece@gmail.com
Requires-Python: >=3.11,<4.0
Classifier: Programming Language :: Python :: 3
Classifier: Programming Language :: Python :: 3.11
Classifier: Programming Language :: Python :: 3.12
Classifier: Programming Language :: Python :: 3.13
Requires-Dist: click (>=8.1,<9.0)
Requires-Dist: notionmanager (>=0.1.24,<0.2.0)
Requires-Dist: python-dotenv (>=1.0,<2.0)
Requires-Dist: python-frontmatter (>=1.1,<2.0)
Requires-Dist: tqdm (>=4.67.1,<5.0.0)
